betterdatamanagement/__init__.py
betterdatamanagement/bdir.py
betterdatamanagement/bfile.py
BetterDataManagement-1.4.1.dist-info/LICENSE
BetterDataManagement-1.4.1.dist-info/METADATA
BetterDataManagement-1.4.1.dist-info/WHEEL
BetterDataManagement-1.4.1.dist-info/top_level.txt
BetterDataManagement-1.4.1.dist-info/RECORD
