Metadata-Version: 2.1
Name: BetterDataManagement
Version: 1.4.1
Summary: A Package designed for a better data management when it comes to both files and directories.
Home-page: https://github.com/MrKelpy/betterdatamanagement
Author: Alexandre Silva // MrKelpy
Author-email: alexandresilva.coding@gmail.com
License: UNKNOWN
Platform: UNKNOWN
Classifier: Programming Language :: Python :: 3
Classifier: License :: OSI Approved :: GNU General Public License v3 (GPLv3)
Classifier: Operating System :: OS Independent
Requires-Python: >=3.6
License-File: LICENSE
Requires-Dist: binaryornot
